pymodaq_plugins_smaract/__init__.py
pymodaq_plugins_smaract/utils.py
pymodaq_plugins_smaract/daq_move_plugins/__init__.py
pymodaq_plugins_smaract/daq_move_plugins/daq_move_SmarActMCS1.py
pymodaq_plugins_smaract/daq_move_plugins/daq_move_SmarActMCS2.py
pymodaq_plugins_smaract/daq_move_plugins/daq_move_SmarActSCU.py
pymodaq_plugins_smaract/daq_viewer_plugins/__init__.py
pymodaq_plugins_smaract/daq_viewer_plugins/plugins_0D/__init__.py
pymodaq_plugins_smaract/daq_viewer_plugins/plugins_1D/__init__.py
pymodaq_plugins_smaract/daq_viewer_plugins/plugins_2D/__init__.py
pymodaq_plugins_smaract/daq_viewer_plugins/plugins_ND/__init__.py
pymodaq_plugins_smaract/hardware/__init__.py
pymodaq_plugins_smaract/hardware/mcs1/MCS1_bindings.py
pymodaq_plugins_smaract/hardware/mcs1/MCS1_wrapper.py
pymodaq_plugins_smaract/hardware/mcs1/MCSControl.dll
pymodaq_plugins_smaract/hardware/mcs1/Readme-Linux.txt
pymodaq_plugins_smaract/hardware/mcs1/__init__.py
pymodaq_plugins_smaract/hardware/mcs1/install_mcs.sh
pymodaq_plugins_smaract/hardware/mcs1/libftchipid.so.0.1.0
pymodaq_plugins_smaract/hardware/mcs1/libftd2xx.so.1
pymodaq_plugins_smaract/hardware/mcs1/libftd2xx.so.1.4.6
pymodaq_plugins_smaract/hardware/mcs1/libmcscontrol.so.3
pymodaq_plugins_smaract/hardware/mcs1/libmcscontrol.so.3.0.28
pymodaq_plugins_smaract/hardware/mcs1/libsmaractio.so.2
pymodaq_plugins_smaract/hardware/mcs1/libsmaractio.so.2.1.2
pymodaq_plugins_smaract/hardware/mcs2/MCS2_bindings.py
pymodaq_plugins_smaract/hardware/mcs2/MCS2_wrapper.py
pymodaq_plugins_smaract/hardware/mcs2/__init__.py
pymodaq_plugins_smaract/hardware/scu/__init__.py
pymodaq_plugins_smaract/hardware/scu/bindings.py
pymodaq_plugins_smaract/hardware/scu/scu_wrapper.py
pymodaq_plugins_smaract/resources/__init__.py
pymodaq_plugins_smaract/resources/config_template.toml
pymodaq_plugins_smaract-3.4.0.dist-info/METADATA
pymodaq_plugins_smaract-3.4.0.dist-info/WHEEL
pymodaq_plugins_smaract-3.4.0.dist-info/entry_points.txt
pymodaq_plugins_smaract-3.4.0.dist-info/licenses/LICENSE
pymodaq_plugins_smaract-3.4.0.dist-info/RECORD
